README.md
setup.cfg
setup.py
flickr_to_50mm/__init__.py
flickr_to_50mm/flickr_to_50mm.py
flickr_to_50mm.egg-info/PKG-INFO
flickr_to_50mm.egg-info/SOURCES.txt
flickr_to_50mm.egg-info/dependency_links.txt
flickr_to_50mm.egg-info/entry_points.txt
flickr_to_50mm.egg-info/requires.txt
flickr_to_50mm.egg-info/top_level.txt