Metadata-Version: 1.1
Name: flickr-to-50mm
Version: 0.92.0
Summary: Configuration generator for 50mm from flickr photosets
Home-page: https://github.com/arahayrabedian/flickr_to_50mm
Author: Ara Hayrabedian
Author-email: flickr_to_50mm.pypi@hyrbdn.com
License: UNKNOWN
Keywords: configuration,50mm,flickr,migrate,migration,export
Platform: UNKNOWN
Classifier: Development Status :: 4 - Beta
Classifier: Intended Audience :: System Administrators
Classifier: License :: OSI Approved :: MIT License
Classifier: Programming Language :: Python :: 3
Classifier: Programming Language :: Python :: 3.3
Classifier: Programming Language :: Python :: 3.4
Classifier: Programming Language :: Python :: 3.5
Classifier: Programming Language :: Python :: 3.6
